<?xml version="1.0" encoding="UTF-8"?>
<MetaDataObject xmlns="http://v8.1c.ru/8.3/MDClasses" xmlns:app="http://v8.1c.ru/8.2/managed-application/core" xmlns:cfg="http://v8.1c.ru/8.1/data/enterprise/current-config" xmlns:cmi="http://v8.1c.ru/8.2/managed-application/cmi" xmlns:ent="http://v8.1c.ru/8.1/data/enterprise" xmlns:lf="http://v8.1c.ru/8.2/managed-application/logform" xmlns:style="http://v8.1c.ru/8.1/data/ui/style" xmlns:sys="http://v8.1c.ru/8.1/data/ui/fonts/system" xmlns:v8="http://v8.1c.ru/8.1/data/core" xmlns:v8ui="http://v8.1c.ru/8.1/data/ui" xmlns:web="http://v8.1c.ru/8.1/data/ui/colors/web" xmlns:win="http://v8.1c.ru/8.1/data/ui/colors/windows" xmlns:xen="http://v8.1c.ru/8.3/xcf/enums" xmlns:xpr="http://v8.1c.ru/8.3/xcf/predef" xmlns:xr="http://v8.1c.ru/8.3/xcf/readable" xmlns:xs="http://www.w3.org/2001/XMLSchema" xmlns:xsi="http://www.w3.org/2001/XMLSchema-instance" version="2.4">
	<Enum uuid="085df068-c2bc-4333-843a-5a9972adbbe6">
		<InternalInfo>
			<xr:GeneratedType name="EnumRef.ВетисНаправлениеОперации" category="Ref">
				<xr:TypeId>3f971d1c-b539-437c-b035-43b5ae235aea</xr:TypeId>
				<xr:ValueId>0c9a17d2-1495-4888-9323-a68afd2dc851</xr:ValueId>
			</xr:GeneratedType>
			<xr:GeneratedType name="EnumManager.ВетисНаправлениеОперации" category="Manager">
				<xr:TypeId>bd3faf84-61ee-4ce2-ac13-c6124031b1aa</xr:TypeId>
				<xr:ValueId>a86ead52-3ff9-41db-8d84-f569a40eaf93</xr:ValueId>
			</xr:GeneratedType>
			<xr:GeneratedType name="EnumList.ВетисНаправлениеОперации" category="List">
				<xr:TypeId>d461858b-5c2d-46da-bfb3-dc4c84352cff</xr:TypeId>
				<xr:ValueId>f084778e-c52e-40c2-a72e-26218d243098</xr:ValueId>
			</xr:GeneratedType>
		</InternalInfo>
		<Properties>
			<Name>ВетисНаправлениеОперации</Name>
			<Synonym>
				<v8:item>
					<v8:lang>ru</v8:lang>
					<v8:content>Направление операции (ветис)</v8:content>
				</v8:item>
			</Synonym>
			<Comment/>
			<UseStandardCommands>false</UseStandardCommands>
			<Characteristics/>
			<QuickChoice>true</QuickChoice>
			<ChoiceMode>BothWays</ChoiceMode>
			<DefaultListForm/>
			<DefaultChoiceForm/>
			<AuxiliaryListForm/>
			<AuxiliaryChoiceForm/>
			<ListPresentation/>
			<ExtendedListPresentation/>
			<Explanation/>
			<ChoiceHistoryOnInput>Auto</ChoiceHistoryOnInput>
		</Properties>
		<ChildObjects>
			<EnumValue uuid="c7babf58-fbb5-48dc-b1cc-e94d1fa90e5d">
				<Properties>
					<Name>Запрос</Name>
					<Synonym>
						<v8:item>
							<v8:lang>ru</v8:lang>
							<v8:content>Запрос</v8:content>
						</v8:item>
					</Synonym>
					<Comment/>
				</Properties>
			</EnumValue>
			<EnumValue uuid="80c16bf7-20b7-43f6-8e93-615fa43efedb">
				<Properties>
					<Name>Ответ</Name>
					<Synonym>
						<v8:item>
							<v8:lang>ru</v8:lang>
							<v8:content>Ответ</v8:content>
						</v8:item>
					</Synonym>
					<Comment/>
				</Properties>
			</EnumValue>
			<EnumValue uuid="aab84a59-1eb5-440d-8a55-cdcb6a549885">
				<Properties>
					<Name>Заявка</Name>
					<Synonym>
						<v8:item>
							<v8:lang>ru</v8:lang>
							<v8:content>Заявка</v8:content>
						</v8:item>
					</Synonym>
					<Comment/>
				</Properties>
			</EnumValue>
			<EnumValue uuid="5ba78e0d-aed7-463b-82f0-58f10ffe1de5">
				<Properties>
					<Name>Прочее</Name>
					<Synonym>
						<v8:item>
							<v8:lang>ru</v8:lang>
							<v8:content>Прочее</v8:content>
						</v8:item>
					</Synonym>
					<Comment/>
				</Properties>
			</EnumValue>
		</ChildObjects>
	</Enum>
</MetaDataObject>